README.txt
setup.cfg
setup.py
Django_G11N.egg-info/PKG-INFO
Django_G11N.egg-info/SOURCES.txt
Django_G11N.egg-info/dependency_links.txt
Django_G11N.egg-info/requires.txt
Django_G11N.egg-info/top_level.txt
django_g11n/__info__.py
django_g11n/__init__.py
django_g11n/admin.py
django_g11n/settings.py
django_g11n/signals.py
django_g11n/urls.py
django_g11n/views.py
django_g11n/management/__init__.py
django_g11n/management/commands/__init__.py
django_g11n/management/commands/currency_by_tld.py
django_g11n/management/commands/g11n_setup.py
django_g11n/management/commands/guess_tld_by_ip.py
django_g11n/management/commands/update_countries.py
django_g11n/management/commands/update_currencies.py
django_g11n/management/commands/update_ipranges.py
django_g11n/management/commands/update_language_countries.py
django_g11n/management/commands/update_languages.py
django_g11n/management/commands/update_regions.py
django_g11n/migrations/0001_initial.py
django_g11n/migrations/0002_add_regions.py
django_g11n/migrations/__init__.py
django_g11n/models/__init__.py
django_g11n/models/core.py
django_g11n/tests/__init__.py
django_g11n/tests/common.py
django_g11n/tests/test_001_command_update_countries.py
django_g11n/tests/test_002_command_update_currencies.py
django_g11n/tests/test_003_command_update_ipranges.py
django_g11n/tests/test_004_command_update_language_countries.py
django_g11n/tests/test_005_command_update_region.py
django_g11n/tests/test_006_command_g11n_setup.py
django_g11n/tests/test_007_request.py
django_g11n/tests/test_008_ipranges.py
django_g11n/tests/test_009_models_str.py
django_g11n/tests/test_999_various.py
django_g11n/tools/__init__.py
django_g11n/tools/by_request.py
django_g11n/tools/country.py
django_g11n/tools/currency.py
django_g11n/tools/fetch.py
django_g11n/tools/ipranges.py
django_g11n/tools/language.py
django_g11n/tools/language_country.py
django_g11n/tools/models.py
django_g11n/tools/region.py
interface/__init__.py
interface/settings.py
interface/urls.py
interface/wsgi.py