Metadata-Version: 1.1
Name: Django-G11N
Version: 1.1.0.1
Summary: Django Globalisation Tools
Home-page: https://bitbucket.org/hellwig/django-g11n
Author: Martin P. Hellwig
Author-email: martin.hellwig@gmail.com
License: BSD
Download-URL: https://bitbucket.org/hellwig/django-g11n/get/1.1.0.1.zip
Keywords: django
Platform: UNKNOWN
Classifier: Programming Language :: Python :: 3
